aws_jupyter/__init__.py
aws_jupyter/_setup_cluster.py
aws_jupyter/check_cluster.py
aws_jupyter/common.py
aws_jupyter/create_cluster.py
aws_jupyter/credentials.py
aws_jupyter/diagnose.py
aws_jupyter/retrieve_files.py
aws_jupyter/run_cluster.py
aws_jupyter/send_files.py
aws_jupyter/set_config.py
aws_jupyter/ssh_headnode.py
aws_jupyter/terminate_cluster.py
aws_jupyter/examples/tmsn-example.py
aws_jupyter/scripts/hello-world.sh
aws_jupyter/scripts/init-worker.sh
aws_jupyter/scripts/install-jupyter-tmsn-for-ami.sh
aws_jupyter/scripts/install-jupyter-tmsn.sh
aws_jupyter/scripts/install-jupyter.sh
aws_jupyter-0.1.24.data/scripts/aws-jupyter
aws_jupyter-0.1.24.data/scripts/launch-aws-jupyter
aws_jupyter-0.1.24.dist-info/METADATA
aws_jupyter-0.1.24.dist-info/WHEEL
aws_jupyter-0.1.24.dist-info/top_level.txt
aws_jupyter-0.1.24.dist-info/RECORD
