Metadata-Version: 2.1
Name: aws-jupyter
Version: 0.1.24
Summary: Launch Jupyter notebook on AWS
Home-page: https://github.com/arapat/aws-jupyter
Author: Julaiti Alafate
Author-email: jalafate@gmail.com
License: UNKNOWN
Platform: UNKNOWN
Requires-Dist: awscli
Requires-Dist: boto
Requires-Dist: pyyaml
